[
    {
        "id":1,
        "title":"THE BEATLES",
        "price":320,
        "description":"Diseño basado en la canción Strawberry Fields Forever.",
        "pictureUrl":"https://cdn.shopify.com/s/files/1/0573/9102/2254/products/Bon-Jovi-Livin-On-a-Prayer-playera-de-mujer_1800x1800.jpg?v=1622681081",
        "stock": 5
    },
    {
        "id":2,
        "title":"THE BEATLES",
        "price":320,
        "description":"Diseño basado en la canción Strawberry Fields Forever.",
        "pictureUrl":"https://cdn.shopify.com/s/files/1/0573/9102/2254/products/Bon-Jovi-Livin-On-a-Prayer-playera-de-mujer_1800x1800.jpg?v=1622681081",
        "stock": 5
    },
    {
        "id":3,
        "title":"THE BEATLES",
        "price":320,
        "description":"Diseño basado en la canción Strawberry Fields Forever.",
        "pictureUrl":"https://cdn.shopify.com/s/files/1/0573/9102/2254/products/Bon-Jovi-Livin-On-a-Prayer-playera-de-mujer_1800x1800.jpg?v=1622681081",
        "stock": 5
    }
]
